sphinx_autopyproject/__init__.py
sphinx_autopyproject/__main__.py
sphinx_autopyproject/auto.py
sphinx_autopyproject/dynamic.py
sphinx_autopyproject/package_metadata.py
sphinx_autopyproject/util.py
sphinx_autopyproject-0.0.2.dist-info/entry_points.txt
sphinx_autopyproject-0.0.2.dist-info/LICENSE
sphinx_autopyproject-0.0.2.dist-info/WHEEL
sphinx_autopyproject-0.0.2.dist-info/METADATA
sphinx_autopyproject-0.0.2.dist-info/RECORD
