Metadata-Version: 2.1
Name: sphinx-autopyproject
Version: 0.0.2
Summary: Inject Sphinx Configuration from pyproject.toml
Author-email: Christian Sachs <sachs.christian@gmail.com>
Requires-Dist: build>=0.8
Requires-Dist: tomli; python_version < '3.11'
Requires-Dist: black ; extra == "check"
Requires-Dist: isort ; extra == "check"
Requires-Dist: pyproject-flake8 ; extra == "check"
Requires-Dist: pylint ; extra == "check"
Requires-Dist: mypy ; extra == "check"
Project-URL: Home, https://github.com/csachs/sphinx-autopyproject
Provides-Extra: check
